__init__.py
__main__.py
report_application/__init__.py
report_application/report_app.py
task_6_report_package-1.0.dist-info/METADATA
task_6_report_package-1.0.dist-info/WHEEL
task_6_report_package-1.0.dist-info/entry_points.txt
task_6_report_package-1.0.dist-info/RECORD
