Metadata-Version: 2.3
Name: task_6_report_package
Version: 1.0
Summary: The application counts and creates racing report.
Author-email: Anton Galkin <anton.galkin@mail.ru>
License-Expression: MIT
Classifier: Operating System :: OS Independent
Classifier: Programming Language :: Python :: 3
Requires-Python: >=3.9
Requires-Dist: iniconfig>=2.0.0
Requires-Dist: packaging>=23.2
Requires-Dist: pluggy>=1.3.0
